README.md
setup.py
py3d/__init__.py
py3d/calculs.py
py3d/droites.py
py3d/plans.py
py3d/points.py
py3d/repere.py
py3d/utils.py
py3d/vecteurs.py
py3d_lib.egg-info/PKG-INFO
py3d_lib.egg-info/SOURCES.txt
py3d_lib.egg-info/dependency_links.txt
py3d_lib.egg-info/requires.txt
py3d_lib.egg-info/top_level.txt