Metadata-Version: 2.1
Name: py3d-lib
Version: 1.0.0
Summary: Un module python en français, qui vise à simplifier les programmes utilisants de la géométrie 2D ou 3D
Home-page: https://github.com/ASionville/py3d
Author: Aubin SIONVILLE
Author-email: aubinsionville@gmail.com
License: MIT
Platform: UNKNOWN
Classifier: License :: OSI Approved :: MIT License
Classifier: Programming Language :: Python :: 3
Classifier: Programming Language :: Python :: 3.7
